pythontwitchbotframework-2.12.3.data/scripts/command_console.py
tests/__init__.py
tests/mock_irc.py
tests/test_events/__init__.py
tests/test_events/test_has_events.py
twitchbot/__init__.py
twitchbot/arena.py
twitchbot/argument_annotations.py
twitchbot/auto_cast_handler.py
twitchbot/bot_package_path.py
twitchbot/cached_property.py
twitchbot/channel.py
twitchbot/colors.py
twitchbot/command.py
twitchbot/command_server.py
twitchbot/command_whitelist.py
twitchbot/config.py
twitchbot/disabled_commands.py
twitchbot/disabled_mods.py
twitchbot/duel.py
twitchbot/emote.py
twitchbot/enums.py
twitchbot/event_util.py
twitchbot/events.py
twitchbot/exceptions.py
twitchbot/irc.py
twitchbot/load_translation_defaults.py
twitchbot/message.py
twitchbot/modloader.py
twitchbot/permission.py
twitchbot/ratelimit.py
twitchbot/ratelimit_twitch_api_queue.py
twitchbot/regex.py
twitchbot/replywaiter.py
twitchbot/shared.py
twitchbot/tags.py
twitchbot/translations.py
twitchbot/api/__init__.py
twitchbot/api/baseapi.py
twitchbot/api/chatters.py
twitchbot/api/streaminfoapi.py
twitchbot/api/userinfoapi.py
twitchbot/bots/__init__.py
twitchbot/bots/basebot.py
twitchbot/builtin_commands/__init__.py
twitchbot/builtin_commands/admin_commands.py
twitchbot/builtin_commands/cmd_management_commands.py
twitchbot/builtin_commands/currency_commands.py
twitchbot/builtin_commands/custom_commands.py
twitchbot/builtin_commands/dbcounter_commands.py
twitchbot/builtin_commands/debug_commands.py
twitchbot/builtin_commands/fun_commands.py
twitchbot/builtin_commands/misc_commands.py
twitchbot/builtin_commands/mod_management_commands.py
twitchbot/builtin_commands/permission_commands.py
twitchbot/builtin_commands/poll_commands.py
twitchbot/builtin_commands/quote_commands.py
twitchbot/builtin_commands/timer_commands.py
twitchbot/builtin_mods/__init__.py
twitchbot/builtin_mods/channel_privmsg_time_updater_mod.py
twitchbot/builtin_mods/channel_stat_updater_mod.py
twitchbot/builtin_mods/loyalty_ticker_mod.py
pythontwitchbotframework-2.12.3.dist-info/LICENSE
pythontwitchbotframework-2.12.3.dist-info/METADATA
pythontwitchbotframework-2.12.3.dist-info/WHEEL
pythontwitchbotframework-2.12.3.dist-info/top_level.txt
pythontwitchbotframework-2.12.3.dist-info/RECORD
