Metadata-Version: 2.1
Name: pythontwitchbotframework
Version: 2.12.3
Summary: asynchronous twitch-bot framework made in pure python
Home-page: https://github.com/sharkbound/PythonTwitchBotFramework
Author: sharkbound
License: MIT
Requires-Python: >=3.6
License-File: LICENSE
Requires-Dist: aiohttp ~=3.9.0
Requires-Dist: SQLAlchemy ~=2.0.0
Requires-Dist: websockets ~=15.0.0
Requires-Dist: async-timeout ~=4.0.0 ; python_version < "3.11"
Requires-Dist: dataclasses ; python_version < "3.7"
